ogmsgui/__init__.py
ogmsgui/ogmsgui.py
ogmsgui/scripts.py
ogmsgui/data/computeModel.json
ogmsgui/ogmsServer2/__init__.py
ogmsgui/ogmsServer2/base.py
ogmsgui/ogmsServer2/constants.py
ogmsgui/ogmsServer2/openModel.py
ogmsgui/ogmsServer2/openUtils/__init__.py
ogmsgui/ogmsServer2/openUtils/exceptions.py
ogmsgui/ogmsServer2/openUtils/http_client.py
ogmsgui/ogmsServer2/openUtils/mdlUtils.py
ogmsgui/ogmsServer2/openUtils/parameterValidator.py
ogmsgui/ogmsServer2/openUtils/stateManager.py
ogmsgui-0.1.9.dist-info/METADATA
ogmsgui-0.1.9.dist-info/WHEEL
ogmsgui-0.1.9.dist-info/top_level.txt
ogmsgui-0.1.9.dist-info/RECORD
