Metadata-Version: 2.1
Name: ogmsgui
Version: 0.1.9
Summary: A GUI package for geographical modeling and simulation
Home-page: https://github.com/MPLebron/ogmsgui
Author: Phileon Ma
Author-email: mpllonggis@gmail.com
Classifier: Programming Language :: Python :: 3
Classifier: License :: OSI Approved :: MIT License
Classifier: Operating System :: OS Independent
Requires-Python: >=3.8
Requires-Dist: ipywidgets
Requires-Dist: ipyfilechooser
Requires-Dist: requests
Requires-Dist: markdown
Requires-Dist: nest_asyncio
Requires-Dist: openai
Requires-Dist: asyncio
